ferne/__init__.py
ferne-0.0.1.dist-info/METADATA
ferne-0.0.1.dist-info/WHEEL
ferne-0.0.1.dist-info/license.txt
ferne-0.0.1.dist-info/top_level.txt
ferne-0.0.1.dist-info/RECORD
